finary_assistant/__init__.py
finary_assistant/__main__.py
finary_assistant/__meta__.py
finary_assistant/assistant.py
finary_assistant/console.py
finary_assistant/copilot/__init__.py
finary_assistant/copilot/copilot.py
finary_assistant/fetch/__init__.py
finary_assistant/fetch/finary_fetch.py
finary_assistant/finary_api/.git
finary_assistant/finary_api/.github/dependabot.yml
finary_assistant/finary_api/.gitignore
finary_assistant/finary_api/LICENSE
finary_assistant/finary_api/README.md
finary_assistant/finary_api/check.sh
finary_assistant/finary_api/credentials.json.tpl
finary_assistant/finary_api/finary_api/__init__.py
finary_assistant/finary_api/finary_api/__main__.py
finary_assistant/finary_api/finary_api/auth.py
finary_assistant/finary_api/finary_api/bank_account_types.py
finary_assistant/finary_api/finary_api/constants.py
finary_assistant/finary_api/finary_api/crypto_chains.py
finary_assistant/finary_api/finary_api/currencies.py
finary_assistant/finary_api/finary_api/generic_asset_categories.py
finary_assistant/finary_api/finary_api/importers/crypto_generic_csv.py
finary_assistant/finary_api/finary_api/importers/cryptocom.py
finary_assistant/finary_api/finary_api/importers/stocks_generic_csv.py
finary_assistant/finary_api/finary_api/institutions.py
finary_assistant/finary_api/finary_api/precious_metals.py
finary_assistant/finary_api/finary_api/scpis.py
finary_assistant/finary_api/finary_api/securities.py
finary_assistant/finary_api/finary_api/signin.py
finary_assistant/finary_api/finary_api/user_cryptos.py
finary_assistant/finary_api/finary_api/user_fonds_euro.py
finary_assistant/finary_api/finary_api/user_generic_assets.py
finary_assistant/finary_api/finary_api/user_holdings_accounts.py
finary_assistant/finary_api/finary_api/user_me.py
finary_assistant/finary_api/finary_api/user_portfolio.py
finary_assistant/finary_api/finary_api/user_precious_metals.py
finary_assistant/finary_api/finary_api/user_real_estates.py
finary_assistant-0.2.1.dist-info/LICENSE
finary_assistant-0.2.1.dist-info/WHEEL
finary_assistant-0.2.1.dist-info/METADATA
finary_assistant-0.2.1.dist-info/RECORD
