Metadata-Version: 2.1
Name: finary-assistant
Version: 0.2.1
Summary: A command line investment assistant to organize your portfolio and simulate its future to reach your life goals.
License: GPLv3
Author: MadeInPierre
Author-email: pielaclau@gmail.com
Requires-Python: >=3.8,<4.0
Classifier: License :: Other/Proprietary License
Classifier: Programming Language :: Python :: 3
Classifier: Programming Language :: Python :: 3.8
Classifier: Programming Language :: Python :: 3.9
Classifier: Programming Language :: Python :: 3.10
Classifier: Programming Language :: Python :: 3.11
Requires-Dist: docopt (==0.6.2)
Requires-Dist: fuzzywuzzy (==0.18.0)
Requires-Dist: requests (==2.28.2)
Requires-Dist: rich (==12.0.1)
